pyemap/__init__.py
pyemap/custom_residues.py
pyemap/data.py
pyemap/emap.py
pyemap/parser.py
pyemap/pathway_analysis.py
pyemap/process_data.py
pyemap/pyemap_exceptions.py
pyemap/shortest_paths.py
pyemap/structures.py
pyemap/utils.py
pyemap/data/README.md
pyemap/data/clusters/0KA.png
pyemap/data/clusters/0KA.svg
pyemap/data/clusters/1CL.png
pyemap/data/clusters/1CL.svg
pyemap/data/clusters/4WV.png
pyemap/data/clusters/4WV.svg
pyemap/data/clusters/4WW.png
pyemap/data/clusters/4WW.svg
pyemap/data/clusters/4WX.png
pyemap/data/clusters/4WX.svg
pyemap/data/clusters/6M0.png
pyemap/data/clusters/6M0.svg
pyemap/data/clusters/8JU.png
pyemap/data/clusters/8JU.svg
pyemap/data/clusters/9S8.png
pyemap/data/clusters/9S8.svg
pyemap/data/clusters/BF8.png
pyemap/data/clusters/BF8.svg
pyemap/data/clusters/BJ8.png
pyemap/data/clusters/BJ8.svg
pyemap/data/clusters/CFM.png
pyemap/data/clusters/CFM.svg
pyemap/data/clusters/CFN.png
pyemap/data/clusters/CFN.svg
pyemap/data/clusters/CLF.png
pyemap/data/clusters/CLF.svg
pyemap/data/clusters/CLP.png
pyemap/data/clusters/CLP.svg
pyemap/data/clusters/CN1.png
pyemap/data/clusters/CN1.svg
pyemap/data/clusters/CNB.png
pyemap/data/clusters/CNB.svg
pyemap/data/clusters/CNF.png
pyemap/data/clusters/CNF.svg
pyemap/data/clusters/CUB.png
pyemap/data/clusters/CUB.svg
pyemap/data/clusters/CUK.png
pyemap/data/clusters/CUK.svg
pyemap/data/clusters/CUM.png
pyemap/data/clusters/CUM.svg
pyemap/data/clusters/CUN.png
pyemap/data/clusters/CUN.svg
pyemap/data/clusters/CUO.png
pyemap/data/clusters/CUO.svg
pyemap/data/clusters/CUV.png
pyemap/data/clusters/CUV.svg
pyemap/data/clusters/CZL.png
pyemap/data/clusters/CZL.svg
pyemap/data/clusters/F3S.png
pyemap/data/clusters/F3S.svg
pyemap/data/clusters/F4S.png
pyemap/data/clusters/F4S.svg
pyemap/data/clusters/FES.png
pyemap/data/clusters/FES.svg
pyemap/data/clusters/FS0.png
pyemap/data/clusters/FS0.svg
pyemap/data/clusters/FS1.png
pyemap/data/clusters/FS1.svg
pyemap/data/clusters/FS2.png
pyemap/data/clusters/FS2.svg
pyemap-2.0.4.dist-info/licenses/LICENSE
pyemap-2.0.4.dist-info/METADATA
pyemap-2.0.4.dist-info/WHEEL
pyemap-2.0.4.dist-info/top_level.txt
pyemap-2.0.4.dist-info/RECORD
