Metadata-Version: 2.4
Name: pyemap
Version: 2.0.4
Summary: PyeMap: A python package for automatic identification of electron and hole transfer pathways in proteins.
Home-page: https://github.com/gayverjr/pyemap/
Author: James Gayvert
Author-email: jrg444@gmail.com
License: BSD 3-Clause
Project-URL: Bug Tracker, https://github.com/gayverjr/pyemap/issues
Classifier: Programming Language :: Python :: 3
Classifier: Operating System :: OS Independent
Requires-Python: >=3.6
License-File: LICENSE
Requires-Dist: numpy<2
Requires-Dist: networkx
Requires-Dist: biopython
Requires-Dist: scipy
Requires-Dist: pillow
Requires-Dist: matplotlib
Requires-Dist: gspan_mining
Requires-Dist: requests
Requires-Dist: pysmiles==1.0.1
Requires-Dist: pandas<2
Dynamic: license-file
